README.md
setup.py
coin_qt_gui/__init__.py
coin_qt_gui/__main__.py
coin_qt_gui/configure.py
coin_qt_gui/downloader.py
coin_qt_gui.egg-info/PKG-INFO
coin_qt_gui.egg-info/SOURCES.txt
coin_qt_gui.egg-info/dependency_links.txt
coin_qt_gui.egg-info/not-zip-safe
coin_qt_gui.egg-info/requires.txt
coin_qt_gui.egg-info/top_level.txt