Metadata-Version: 1.0
Name: coin-qt-gui
Version: 0.1.2
Summary: Vizualizar cotação de criptomoedas
Home-page: https://github.com/Brunopvh/coin-qt-gui
Author: Bruno Chaves
Author-email: brunodasill@gmail.com
License: MIT
Project-URL: Código fonte, https://github.com/Brunopvh/coin-qt-gui
Project-URL: Download, https://github.com/Brunopvh/coin-qt-gui/archive/refs/heads/master.zip
Platform: UNKNOWN
